kloggpro/__init__.py
kloggpro/klimalogg.py
kloggpro-0.0.4.dist-info/LICENSE
kloggpro-0.0.4.dist-info/METADATA
kloggpro-0.0.4.dist-info/WHEEL
kloggpro-0.0.4.dist-info/top_level.txt
kloggpro-0.0.4.dist-info/RECORD
