Metadata-Version: 2.1
Name: kloggpro
Version: 0.0.4
Summary: Package for TFA KlimaLoggPro-Driver to use with Home Assistant
Home-page: https://github.com/z8i/kloggpro
Author: Martin (z8i)
Author-email: github@z8i.de
Classifier: Programming Language :: Python :: 3
Classifier: Development Status :: 3 - Alpha
Classifier: License :: OSI Approved :: GNU General Public License v3 (GPLv3)
Classifier: Operating System :: POSIX :: Linux
Requires-Python: >=3.6
License-File: LICENSE
Requires-Dist: pyusb
